{"summaries":[{"symbol":{"__symbol":0},"metadata":{"__symbolic":"class","statics":{"CONSTRUCTORS":{"rectangle":{"__symbol":1},"circle":{"__symbol":2},"polygon":{"__symbol":3}}}}}],"symbols":[{"__symbol":0,"name":"AreaFactory","filePath":"/home/yuriy/Work/imageMapEditor/src/area-factory.class.d.ts"},{"__symbol":1,"name":"Rectangle","filePath":"/home/yuriy/Work/imageMapEditor/src/rectangle.class.d.ts"},{"__symbol":2,"name":"Circle","filePath":"/home/yuriy/Work/imageMapEditor/src/circle.class.d.ts"},{"__symbol":3,"name":"Polygon","filePath":"/home/yuriy/Work/imageMapEditor/src/polygon.class.d.ts"}]}