{"summaries":[{"symbol":{"__symbol":0},"metadata":{"__symbolic":"class","statics":{"SIZE":5,"SIZENum":15,"OFFSET":{"__symbolic":"pre","operator":"-","operand":{"__symbolic":"call","expression":{"__symbolic":"select","expression":{"__symbol":1},"member":"ceil"},"arguments":[{"__symbolic":"binop","operator":"/","left":{"__symbolic":"select","expression":{"__symbol":0},"member":"SIZE"},"right":2}]}},"CLASS_NAME":"helper","ACTIONS_TO_CURSORS":{"move":"move","editLeft":"e-resize","editRight":"w-resize","editTop":"n-resize","editBottom":"s-resize","editTopLeft":"nw-resize","editTopRight":"ne-resize","editBottomLeft":"sw-resize","editBottomRight":"se-resize","pointMove":"pointer","number":"default"}}}}],"symbols":[{"__symbol":0,"name":"Helper","filePath":"/home/yuriy/Work/imageMapEditor/src/helper.class.d.ts"},{"__symbol":1,"name":"Math","filePath":"/home/yuriy/Work/imageMapEditor/src/helper.class.d.ts"}]}